parallel_processor/__init__.py
parallel_processor-0.1.7.dist-info/METADATA
parallel_processor-0.1.7.dist-info/WHEEL
parallel_processor-0.1.7.dist-info/top_level.txt
parallel_processor-0.1.7.dist-info/RECORD
