Metadata-Version: 2.1
Name: parallel-processor
Version: 0.1.7
Summary: Parallelling Data Processor
Home-page: https://github.com/Fakekid/parallel-processor
Author: Xiaolei Lian,Yue Wang,Tingting Gong,Hang Deng
Author-email: lian19931201@gmail.com,wangyue29@tal.com,gongtingting@safeis.cn,denghang@safeis.cn
License: MIT
Requires-Python: >=3.6
Requires-Dist: numpy (>=1.14.3)
